__init__.py
case.py
consts.py
func.py
OrangeGenerator-0.1.dist-info/WHEEL
OrangeGenerator-0.1.dist-info/METADATA
OrangeGenerator-0.1.dist-info/RECORD
